fast2app/__init__.py
fast2app/command_line/__init__.py
fast2app/command_line/fast2nuxt.py
fast2app/export/__init__.py
fast2app/export/nuxt/__init__.py
fast2app/export/nuxt/build_nuxt_server.py
fast2app/export/nuxt/config.toml
fast2app/export/nuxt/nuxt_server_generation.py
fast2app/export/nuxt/templates/apiFunction.ts
fast2app/export/nuxt/templates/apiHeader.ts
fast2app/export/nuxt/templates/apiImport.ts
fast2app/export/nuxt/templates/apiUsage.ts
fast2app/export/nuxt/templates/composableFunction.ts
fast2app/export/nuxt/templates/composableHeader.ts
fast2app/export/nuxt/templates/composableImport.ts
fast2app/export/nuxt/templates/composableUsage.ts
fast2app/export/type_script/__init__.py
fast2app/export/type_script/generate_interfaces.py
fast2app/export/type_script/mapping.py
fast2app/export/type_script/type_conversion.py
fast2app/parsing/__init__.py
fast2app/parsing/models.py
fast2app/parsing/routes.py
fast2app/parsing/validity_checks.py
fast2app/utils/__init__.py
fast2app/utils/naming.py
fast2app/utils/toml.py
fast2app-1.2.4.dist-info/LICENSE
fast2app-1.2.4.dist-info/METADATA
fast2app-1.2.4.dist-info/WHEEL
fast2app-1.2.4.dist-info/entry_points.txt
fast2app-1.2.4.dist-info/RECORD
