Metadata-Version: 2.3
Name: fast2app
Version: 1.2.4
Summary: A simple tool designed to automatically generate usable types, functions, and other useful server-side code from a list of [FastAPI](https://fastapi.tiangolo.com/) application to a given framework.
Keywords: fastapi,nuxt,composable,api,generation,typescript,framework,backend,frontend
Author: Emmanule Nicolle
Author-email: emmanuel.nicolle@mydh.io
Requires-Python: >=3.11
Classifier: Programming Language :: Python :: 3
Classifier: Programming Language :: Python :: 3.11
Classifier: Programming Language :: Python :: 3.12
Classifier: Programming Language :: Python :: 3.13
Requires-Dist: astroid
Requires-Dist: camel_converter
Requires-Dist: fastapi
Requires-Dist: jinja2
Requires-Dist: pydantic
Requires-Dist: pydantic-to-typescript2
Requires-Dist: regex
Requires-Dist: toml
Project-URL: Bug Tracker, https://git.mydh.io/shared/fast2app/-/issues/?sort=priority&state=opened&label_name%5B%5D=bug&first_page_size=20
Project-URL: Contact and contribution, https://helpdesk.mydh.io/contact-form
Project-URL: Homepage, https://git.mydh.io/shared/fast2app
Project-URL: Help Desk, https://helpdesk.mydh.io/issue-form
Project-URL: Nuxt Documentation, https://git.mydh.io/shared/fast2app/-/blob/development/NUXT_DOCUMENTATION.md
